what2read/__init__.py
what2read/cli.py
what2read-0.0.1.dev1.dist-info/METADATA
what2read-0.0.1.dev1.dist-info/WHEEL
what2read-0.0.1.dev1.dist-info/entry_points.txt
what2read-0.0.1.dev1.dist-info/RECORD
